{"_via_settings":{"ui":{"annotation_editor_height":25,"annotation_editor_fontsize":0.8,"leftsidebar_width":18,"image_grid":{"img_height":80,"rshape_fill":"none","rshape_fill_opacity":0.3,"rshape_stroke":"yellow","rshape_stroke_width":2,"show_region_shape":true,"show_image_policy":"all"},"image":{"region_label":"Type","region_color":"__via_default_region_color__","region_label_font":"10px Sans","on_image_annotation_editor_placement":"NEAR_REGION"}},"core":{"buffer_size":18,"filepath":{},"default_filepath":""},"project":{"name":"Dimitris_4"}},"_via_img_metadata":{"Ghost_img_D00270414.jpg38186":{"filename":"Ghost_img_D00270414.jpg","size":38186,"regions":[{"shape_attributes":{"name":"polyline","all_points_x":[151,167,166,228,232,241,271,257,248,242,232,232,194,165,149,132,129,149,152],"all_points_y":[391,391,358,360,394,393,293,274,292,299,298,286,276,289,270,295,304,390,390]},"region_attributes":{"Type":"Rays"}}],"file_attributes":{}},"Ghost_img_D00360575.jpg38897":{"filename":"Ghost_img_D00360575.jpg","size":38897,"regions":[{"shape_attributes":{"name":"ellipse","cx":152,"cy":381,"rx":26.476,"ry":5,"theta":0.19},"region_attributes":{"Type":"Bright"}},{"shape_attributes":{"name":"circle","cx":230,"cy":54,"r":16},"region_attributes":{"Type":"Bright"}},{"shape_attributes":{"name":"polyline","all_points_x":[230,255,273,272,251,254,245,230,231],"all_points_y":[12,10,28,38,29,46,41,14,14]},"region_attributes":{"Type":"Rays"}},{"shape_attributes":{"name":"circle","cx":207,"cy":173,"r":125.196},"region_attributes":{"Type":"Faint"}}],"file_attributes":{}},"Ghost_img_D00239707.jpg37617":{"filename":"Ghost_img_D00239707.jpg","size":37617,"regions":[{"shape_attributes":{"name":"polyline","all_points_x":[113,112,96,96,111,137,158,145,167,193,147,113,113],"all_points_y":[14,42,42,59,60,105,102,62,69,67,12,13,19]},"region_attributes":{"Type":"Rays"}},{"shape_attributes":{"name":"polyline","all_points_x":[23,16,16,34,31,23],"all_points_y":[218,229,241,249,220,217]},"region_attributes":{"Type":"Bright"}}],"file_attributes":{}},"Ghost_img_D00240503.jpg37925":{"filename":"Ghost_img_D00240503.jpg","size":37925,"regions":[{"shape_attributes":{"name":"polyline","all_points_x":[398,349,357,399,399,391],"all_points_y":[197,188,171,183,197,197]},"region_attributes":{"Type":"Rays"}},{"shape_attributes":{"name":"polyline","all_points_x":[398,352,353,397,398,397],"all_points_y":[210,214,226,230,230,209]},"region_attributes":{"Type":"Rays"}},{"shape_attributes":{"name":"circle","cx":162,"cy":151,"r":11},"region_attributes":{"Type":"Bright"}}],"file_attributes":{}},"Ghost_img_D00237444.jpg35593":{"filename":"Ghost_img_D00237444.jpg","size":35593,"regions":[{"shape_attributes":{"name":"polyline","all_points_x":[397,378,299,302,399,398,395],"all_points_y":[231,231,199,171,215,231,231]},"region_attributes":{"Type":"Rays"}},{"shape_attributes":{"name":"polyline","all_points_x":[379,331,347,378,378],"all_points_y":[239,236,253,256,238]},"region_attributes":{"Type":"Rays"}}],"file_attributes":{}},"Ghost_img_D00487224.jpg40966":{"filename":"Ghost_img_D00487224.jpg","size":40966,"regions":[{"shape_attributes":{"name":"circle","cx":296,"cy":65,"r":14},"region_attributes":{"Type":"Bright"}},{"shape_attributes":{"name":"polyline","all_points_x":[81,279,341,331,293,237,184,135,97,80],"all_points_y":[158,309,231,131,85,60,57,75,111,159]},"region_attributes":{"Type":"Faint"}},{"shape_attributes":{"name":"circle","cx":254,"cy":126,"r":83},"region_attributes":{"Type":"Faint"}}],"file_attributes":{}},"Ghost_img_D00510773.jpg35141":{"filename":"Ghost_img_D00510773.jpg","size":35141,"regions":[{"shape_attributes":{"name":"circle","cx":133,"cy":215,"r":14},"region_attributes":{"Type":"Bright"}}],"file_attributes":{}},"Ghost_img_D00799119.jpg42697":{"filename":"Ghost_img_D00799119.jpg","size":42697,"regions":[{"shape_attributes":{"name":"ellipse","cx":316,"cy":204,"rx":26,"ry":38.053,"theta":-0.053},"region_attributes":{"Type":"Bright"}},{"shape_attributes":{"name":"circle","cx":73,"cy":196,"r":15},"region_attributes":{"Type":"Bright"}},{"shape_attributes":{"name":"polyline","all_points_x":[1,45,49,49,38,24,2,0,1,5],"all_points_y":[203,203,205,213,223,230,227,219,202,204]},"region_attributes":{"Type":"Bright"}},{"shape_attributes":{"name":"polyline","all_points_x":[1,46,40,24,7,2,2,2,2],"all_points_y":[186,186,175,170,170,173,174,184,186]},"region_attributes":{"Type":"Bright"}},{"shape_attributes":{"name":"circle","cx":124,"cy":199,"r":73},"region_attributes":{"Type":"Faint"}},{"shape_attributes":{"name":"circle","cx":164,"cy":201,"r":120.067},"region_attributes":{"Type":"Faint"}}],"file_attributes":{}},"Ghost_img_D00701094.jpg40298":{"filename":"Ghost_img_D00701094.jpg","size":40298,"regions":[{"shape_attributes":{"name":"ellipse","cx":166,"cy":172,"rx":40.05,"ry":37,"theta":3.092},"region_attributes":{"Type":"Faint"}},{"shape_attributes":{"name":"circle","cx":256,"cy":241,"r":16},"region_attributes":{"Type":"Faint"}},{"shape_attributes":{"name":"polyline","all_points_x":[305,266,266,300,303,292,270,254,255,278,306,302],"all_points_y":[253,250,261,264,271,281,279,266,243,234,238,255]},"region_attributes":{"Type":"Faint"}}],"file_attributes":{}},"Ghost_img_D00243671.jpg43091":{"filename":"Ghost_img_D00243671.jpg","size":43091,"regions":[{"shape_attributes":{"name":"ellipse","cx":112,"cy":70,"rx":35.468,"ry":16,"theta":-0.706},"region_attributes":{"Type":"Bright"}},{"shape_attributes":{"name":"circle","cx":278,"cy":318,"r":13.601},"region_attributes":{"Type":"Bright"}},{"shape_attributes":{"name":"circle","cx":246,"cy":270,"r":76},"region_attributes":{"Type":"Bright"}},{"shape_attributes":{"name":"circle","cx":217,"cy":228,"r":119.105},"region_attributes":{"Type":"Bright"}},{"shape_attributes":{"name":"polyline","all_points_x":[283,292,292,283,281,280,285],"all_points_y":[392,392,352,351,369,390,391]},"region_attributes":{"Type":"Bright"}}],"file_attributes":{}},"Ghost_img_D00251360.jpg37064":{"filename":"Ghost_img_D00251360.jpg","size":37064,"regions":[{"shape_attributes":{"name":"polyline","all_points_x":[377,315,375,379,377,376],"all_points_y":[157,161,131,139,158,158]},"region_attributes":{"Type":"Rays"}},{"shape_attributes":{"name":"polyline","all_points_x":[384,316,360,399,399,384],"all_points_y":[171,198,202,185,172,171]},"region_attributes":{"Type":"Rays"}}],"file_attributes":{}},"Ghost_img_D00396006.jpg33394":{"filename":"Ghost_img_D00396006.jpg","size":33394,"regions":[{"shape_attributes":{"name":"polyline","all_points_x":[230,268,261,248,234,234,231],"all_points_y":[11,11,29,29,28,26,12]},"region_attributes":{"Type":"Faint"}},{"shape_attributes":{"name":"ellipse","cx":169,"cy":325,"rx":31.385,"ry":20,"theta":0.392},"region_attributes":{"Type":"Faint"}},{"shape_attributes":{"name":"polyline","all_points_x":[80,93,133,207,269,306,254,201,82],"all_points_y":[204,247,288,313,302,271,221,250,207]},"region_attributes":{"Type":"Faint"}}],"file_attributes":{}},"Ghost_img_D00686822.jpg42584":{"filename":"Ghost_img_D00686822.jpg","size":42584,"regions":[{"shape_attributes":{"name":"ellipse","cx":305,"cy":250,"rx":27,"ry":39.357,"theta":-2.667},"region_attributes":{"Type":"Faint"}},{"shape_attributes":{"name":"polyline","all_points_x":[22,63,66,61,20,21],"all_points_y":[124,124,124,104,105,124]},"region_attributes":{"Type":"Bright"}},{"shape_attributes":{"name":"polyline","all_points_x":[21,59,43,22,21],"all_points_y":[140,139,157,154,141]},"region_attributes":{"Type":"Bright"}},{"shape_attributes":{"name":"polyline","all_points_x":[149,168,241,289,290,217,231,200,149],"all_points_y":[241,311,293,221,131,132,197,243,246]},"region_attributes":{"Type":"Faint"}}],"file_attributes":{}},"Ghost_img_D00243229.jpg36052":{"filename":"Ghost_img_D00243229.jpg","size":36052,"regions":[{"shape_attributes":{"name":"polyline","all_points_x":[111,110,104,113,140,115,123,182,201,136,110,110],"all_points_y":[14,42,42,98,96,17,15,109,84,7,13,20]},"region_attributes":{"Type":"Rays"}}],"file_attributes":{}},"Ghost_img_D00240804.jpg36113":{"filename":"Ghost_img_D00240804.jpg","size":36113,"regions":[{"shape_attributes":{"name":"polyline","all_points_x":[111,109,106,117,137,114,121,182,184,135,112,110],"all_points_y":[12,42,42,80,77,15,14,107,65,10,11,13]},"region_attributes":{"Type":"Rays"}},{"shape_attributes":{"name":"circle","cx":221,"cy":189,"r":10},"region_attributes":{"Type":"Faint"}},{"shape_attributes":{"name":"polyline","all_points_x":[173,213,213,169,172],"all_points_y":[196,197,182,182,195]},"region_attributes":{"Type":"Rays"}}],"file_attributes":{}},"Ghost_img_D00776109.jpg36907":{"filename":"Ghost_img_D00776109.jpg","size":36907,"regions":[{"shape_attributes":{"name":"circle","cx":224,"cy":128,"r":12.042},"region_attributes":{"Type":"Bright"}},{"shape_attributes":{"name":"circle","cx":225,"cy":128,"r":24},"region_attributes":{"Type":"Faint"}},{"shape_attributes":{"name":"ellipse","cx":191,"cy":230,"rx":40,"ry":38.118,"theta":3.063},"region_attributes":{"Type":"Faint"}},{"shape_attributes":{"name":"circle","cx":206,"cy":188,"r":125},"region_attributes":{"Type":"Faint"}}],"file_attributes":{}},"Ghost_img_D00703260.jpg36404":{"filename":"Ghost_img_D00703260.jpg","size":36404,"regions":[{"shape_attributes":{"name":"circle","cx":300,"cy":94,"r":18},"region_attributes":{"Type":"Bright"}},{"shape_attributes":{"name":"circle","cx":302,"cy":97,"r":30.017},"region_attributes":{"Type":"Faint"}},{"shape_attributes":{"name":"ellipse","cx":149,"cy":254,"rx":38.013,"ry":30,"theta":0.617},"region_attributes":{"Type":"Faint"}},{"shape_attributes":{"name":"polyline","all_points_x":[87,104,160,247,290,255,209,128,89,86],"all_points_y":[206,256,300,315,294,229,241,205,207,207]},"region_attributes":{"Type":"Faint"}}],"file_attributes":{}},"Ghost_img_D00484509.jpg39898":{"filename":"Ghost_img_D00484509.jpg","size":39898,"regions":[{"shape_attributes":{"name":"circle","cx":260,"cy":44,"r":19.105},"region_attributes":{"Type":"Bright"}},{"shape_attributes":{"name":"circle","cx":259,"cy":45,"r":29},"region_attributes":{"Type":"Faint"}},{"shape_attributes":{"name":"ellipse","cx":165,"cy":291,"rx":36.878,"ry":27,"theta":-2.433},"region_attributes":{"Type":"Faint"}},{"shape_attributes":{"name":"circle","cx":214,"cy":173,"r":119.004},"region_attributes":{"Type":"Faint"}}],"file_attributes":{}},"Ghost_img_D00281645.jpg36076":{"filename":"Ghost_img_D00281645.jpg","size":36076,"regions":[{"shape_attributes":{"name":"polyline","all_points_x":[288,320,320,286,269,306,296,237,226,289],"all_points_y":[360,360,332,248,251,340,349,285,290,362]},"region_attributes":{"Type":"Rays"}}],"file_attributes":{}},"Ghost_img_D00158340.jpg35008":{"filename":"Ghost_img_D00158340.jpg","size":35008,"regions":[{"shape_attributes":{"name":"polyline","all_points_x":[250,282,289,261,271,261,233,217,249],"all_points_y":[10,9,69,58,15,11,66,50,10]},"region_attributes":{"Type":"Rays"}},{"shape_attributes":{"name":"circle","cx":84,"cy":222,"r":15},"region_attributes":{"Type":"Bright"}},{"shape_attributes":{"name":"polyline","all_points_x":[141,191,158,123,112,112,142],"all_points_y":[391,333,326,382,373,389,391]},"region_attributes":{"Type":"Rays"}}],"file_attributes":{}},"Ghost_img_D00281667.jpg36761":{"filename":"Ghost_img_D00281667.jpg","size":36761,"regions":[{"shape_attributes":{"name":"polyline","all_points_x":[0,77,86,2,1],"all_points_y":[222,247,214,207,222]},"region_attributes":{"Type":"Rays"}},{"shape_attributes":{"name":"polyline","all_points_x":[2,60,33,1,1],"all_points_y":[186,186,163,174,185]},"region_attributes":{"Type":"Rays"}}],"file_attributes":{}},"Ghost_img_D00247637.jpg34833":{"filename":"Ghost_img_D00247637.jpg","size":34833,"regions":[{"shape_attributes":{"name":"polyline","all_points_x":[52,80,86,51],"all_points_y":[75,100,73,73]},"region_attributes":{"Type":"Rays"}},{"shape_attributes":{"name":"polyline","all_points_x":[380,306,306,379,379],"all_points_y":[291,291,263,267,293]},"region_attributes":{"Type":"Rays"}},{"shape_attributes":{"name":"polyline","all_points_x":[309,379,379,331,308],"all_points_y":[222,257,234,198,223]},"region_attributes":{"Type":"Rays"}},{"shape_attributes":{"name":"polyline","all_points_x":[153,134,128,151,153],"all_points_y":[391,390,372,364,393]},"region_attributes":{"Type":"Rays"}}],"file_attributes":{}},"Ghost_img_D00491193.jpg36372":{"filename":"Ghost_img_D00491193.jpg","size":36372,"regions":[{"shape_attributes":{"name":"ellipse","cx":45,"cy":156,"rx":17.029,"ry":16,"theta":-0.059},"region_attributes":{"Type":"Bright"}}],"file_attributes":{}},"Ghost_img_D00261167.jpg37653":{"filename":"Ghost_img_D00261167.jpg","size":37653,"regions":[{"shape_attributes":{"name":"polyline","all_points_x":[186,209,212,200,186,184,186],"all_points_y":[361,364,344,335,339,352,360]},"region_attributes":{"Type":"Bright"}},{"shape_attributes":{"name":"circle","cx":198,"cy":292,"r":69.029},"region_attributes":{"Type":"Faint"}},{"shape_attributes":{"name":"circle","cx":199,"cy":238,"r":127.193},"region_attributes":{"Type":"Faint"}},{"shape_attributes":{"name":"polyline","all_points_x":[93,114,169,245,306,314,291,287,232,232,167,167,111,112,94],"all_points_y":[44,76,99,103,63,42,43,10,12,41,40,14,12,43,43]},"region_attributes":{"Type":"Faint"}},{"shape_attributes":{"name":"polyline","all_points_x":[168,152,111,95,111,168,271,298,300,278,246,231,229,167,168],"all_points_y":[392,392,358,300,231,206,232,287,319,372,394,392,354,357,393]},"region_attributes":{"Type":"Faint"}}],"file_attributes":{}},"Ghost_img_D00264198.jpg35941":{"filename":"Ghost_img_D00264198.jpg","size":35941,"regions":[{"shape_attributes":{"name":"circle","cx":112,"cy":254,"r":13},"region_attributes":{"Type":"Bright"}},{"shape_attributes":{"name":"circle","cx":110,"cy":256,"r":24},"region_attributes":{"Type":"Faint"}}],"file_attributes":{}},"Ghost_img_D00804812.jpg37561":{"filename":"Ghost_img_D00804812.jpg","size":37561,"regions":[{"shape_attributes":{"name":"circle","cx":141,"cy":326,"r":19},"region_attributes":{"Type":"Faint"}}],"file_attributes":{}},"Ghost_img_D00162299.jpg38967":{"filename":"Ghost_img_D00162299.jpg","size":38967,"regions":[{"shape_attributes":{"name":"ellipse","cx":165,"cy":139,"rx":39,"ry":32,"theta":-0.395},"region_attributes":{"Type":"Bright"}},{"shape_attributes":{"name":"circle","cx":264,"cy":323,"r":18},"region_attributes":{"Type":"Bright"}},{"shape_attributes":{"name":"circle","cx":262,"cy":325,"r":26},"region_attributes":{"Type":"Faint"}},{"shape_attributes":{"name":"circle","cx":244,"cy":286,"r":13},"region_attributes":{"Type":"Bright"}},{"shape_attributes":{"name":"circle","cx":209,"cy":233,"r":123},"region_attributes":{"Type":"Faint"}}],"file_attributes":{}},"Ghost_img_D00578320.jpg41473":{"filename":"Ghost_img_D00578320.jpg","size":41473,"regions":[{"shape_attributes":{"name":"ellipse","cx":163,"cy":79,"rx":37.108,"ry":22,"theta":2.897},"region_attributes":{"Type":"Bright"}},{"shape_attributes":{"name":"circle","cx":235,"cy":327,"r":17},"region_attributes":{"Type":"Bright"}},{"shape_attributes":{"name":"polyline","all_points_x":[230,280,276,252,231,231],"all_points_y":[391,390,363,341,349,390]},"region_attributes":{"Type":"Bright"}},{"shape_attributes":{"name":"circle","cx":225,"cy":276,"r":78.006},"region_attributes":{"Type":"Faint"}},{"shape_attributes":{"name":"circle","cx":208,"cy":222,"r":130.062},"region_attributes":{"Type":"Faint"}},{"shape_attributes":{"name":"polyline","all_points_x":[42,48,88,167,247,294,298,268,233,233,172,167,112,112,83,84,84,83,48,51,44],"all_points_y":[108,157,204,227,211,141,75,19,9,42,38,12,12,46,44,66,69,75,76,108,108]},"region_attributes":{"Type":"Faint"}}],"file_attributes":{}},"Ghost_img_D00670009.jpg42427":{"filename":"Ghost_img_D00670009.jpg","size":42427,"regions":[{"shape_attributes":{"name":"circle","cx":208,"cy":32,"r":16},"region_attributes":{"Type":"Bright"}},{"shape_attributes":{"name":"circle","cx":197,"cy":238,"r":22.023},"region_attributes":{"Type":"Bright"}},{"shape_attributes":{"name":"ellipse","cx":199,"cy":181,"rx":37.121,"ry":30,"theta":-0.081},"region_attributes":{"Type":"Bright"}}],"file_attributes":{}},"Ghost_img_D00403482.jpg38797":{"filename":"Ghost_img_D00403482.jpg","size":38797,"regions":[{"shape_attributes":{"name":"circle","cx":305,"cy":149,"r":14},"region_attributes":{"Type":"Bright"}},{"shape_attributes":{"name":"circle","cx":354,"cy":127,"r":19.416},"region_attributes":{"Type":"Bright"}},{"shape_attributes":{"name":"circle","cx":351,"cy":128,"r":31},"region_attributes":{"Type":"Bright"}},{"shape_attributes":{"name":"ellipse","cx":113,"cy":241,"rx":30,"ry":35.847,"theta":-0.401},"region_attributes":{"Type":"Faint"}}],"file_attributes":{}},"Ghost_img_D00157884.jpg37737":{"filename":"Ghost_img_D00157884.jpg","size":37737,"regions":[{"shape_attributes":{"name":"polyline","all_points_x":[380,320,320,380,378],"all_points_y":[110,116,139,131,107]},"region_attributes":{"Type":"Faint"}},{"shape_attributes":{"name":"polyline","all_points_x":[337,380,383,336,336,341],"all_points_y":[167,142,163,170,166,166]},"region_attributes":{"Type":"Rays"}},{"shape_attributes":{"name":"polyline","all_points_x":[232,232,257,256,232],"all_points_y":[393,345,347,392,392]},"region_attributes":{"Type":"Rays"}}],"file_attributes":{}},"Ghost_img_D00252782.jpg34737":{"filename":"Ghost_img_D00252782.jpg","size":34737,"regions":[{"shape_attributes":{"name":"polyline","all_points_x":[352,378,327,285,352,354],"all_points_y":[295,295,237,239,294,295]},"region_attributes":{"Type":"Rays"}},{"shape_attributes":{"name":"polyline","all_points_x":[266,348,349,277,263],"all_points_y":[301,328,309,266,300]},"region_attributes":{"Type":"Rays"}}],"file_attributes":{}},"Ghost_img_D00720402.jpg38535":{"filename":"Ghost_img_D00720402.jpg","size":38535,"regions":[{"shape_attributes":{"name":"ellipse","cx":223,"cy":348,"rx":37.336,"ry":15,"theta":-0.134},"region_attributes":{"Type":"Bright"}},{"shape_attributes":{"name":"ellipse","cx":180,"cy":62,"rx":15,"ry":16,"theta":0},"region_attributes":{"Type":"Bright"}},{"shape_attributes":{"name":"polyline","all_points_x":[200,142,142,162,186,200],"all_points_y":[11,8,17,30,28,12]},"region_attributes":{"Type":"Bright"}},{"shape_attributes":{"name":"polyline","all_points_x":[95,146,184,247,247,96],"all_points_y":[95,51,42,50,75,96]},"region_attributes":{"Type":"Faint"}}],"file_attributes":{}},"Ghost_img_D00361667.jpg35267":{"filename":"Ghost_img_D00361667.jpg","size":35267,"regions":[{"shape_attributes":{"name":"polyline","all_points_x":[81,109,109,72,94,110,121,128,125,110,93,81,82],"all_points_y":[71,71,89,88,105,101,98,79,56,44,44,48,71]},"region_attributes":{"Type":"Rays"}},{"shape_attributes":{"name":"ellipse","cx":258,"cy":271,"rx":33,"ry":30.48,"theta":2.287},"region_attributes":{"Type":"Bright"}},{"shape_attributes":{"name":"circle","cx":130,"cy":112,"r":16.031},"region_attributes":{"Type":"Bright"}},{"shape_attributes":{"name":"circle","cx":161,"cy":147,"r":81},"region_attributes":{"Type":"Faint"}},{"shape_attributes":{"name":"circle","cx":177,"cy":168,"r":128.141},"region_attributes":{"Type":"Faint"}}],"file_attributes":{}},"Ghost_img_D00270231.jpg35564":{"filename":"Ghost_img_D00270231.jpg","size":35564,"regions":[{"shape_attributes":{"name":"polyline","all_points_x":[81,170,175,109,81,81],"all_points_y":[44,130,86,43,42,45]},"region_attributes":{"Type":"Rays"}},{"shape_attributes":{"name":"polyline","all_points_x":[82,67,88,119,81],"all_points_y":[75,75,122,131,75]},"region_attributes":{"Type":"Rays"}}],"file_attributes":{}},"Ghost_img_D00274018.jpg33948":{"filename":"Ghost_img_D00274018.jpg","size":33948,"regions":[{"shape_attributes":{"name":"polyline","all_points_x":[174,202,188,140,174],"all_points_y":[42,43,144,163,43]},"region_attributes":{"Type":"Rays"}},{"shape_attributes":{"name":"polyline","all_points_x":[213,222,262,242,256,240,231,231,213],"all_points_y":[42,171,168,66,61,10,10,43,43]},"region_attributes":{"Type":"Rays"}}],"file_attributes":{}},"Ghost_img_D00717821.jpg34449":{"filename":"Ghost_img_D00717821.jpg","size":34449,"regions":[{"shape_attributes":{"name":"circle","cx":105,"cy":156,"r":15.133},"region_attributes":{"Type":"Bright"}},{"shape_attributes":{"name":"circle","cx":130,"cy":169,"r":14.036},"region_attributes":{"Type":"Faint"}},{"shape_attributes":{"name":"circle","cx":116,"cy":101,"r":17},"region_attributes":{"Type":"Faint"}},{"shape_attributes":{"name":"ellipse","cx":245,"cy":220,"rx":40,"ry":32,"theta":-0.644},"region_attributes":{"Type":"Faint"}}],"file_attributes":{}},"Ghost_img_D00239722.jpg36442":{"filename":"Ghost_img_D00239722.jpg","size":36442,"regions":[{"shape_attributes":{"name":"polyline","all_points_x":[17,21,49,50,56,105,72,80,117,124,179,179,134,137,121,99,127,104,38,16,19,16],"all_points_y":[164,107,100,76,78,94,99,107,113,129,160,169,163,174,176,171,199,199,165,167,163,162]},"region_attributes":{"Type":"Rays"}},{"shape_attributes":{"name":"polyline","all_points_x":[22,40,88,88,69,72,71,75,51,51,20,20,26],"all_points_y":[241,241,208,221,247,259,268,301,306,298,294,237,242]},"region_attributes":{"Type":"Rays"}},{"shape_attributes":{"name":"polyline","all_points_x":[349,349,378,372,347,332,338,349],"all_points_y":[69,104,105,116,116,96,72,69]},"region_attributes":{"Type":"Rays"}}],"file_attributes":{}},"Ghost_img_D00704854.jpg38370":{"filename":"Ghost_img_D00704854.jpg","size":38370,"regions":[{"shape_attributes":{"name":"circle","cx":244,"cy":81,"r":16},"region_attributes":{"Type":"Faint"}},{"shape_attributes":{"name":"polyline","all_points_x":[248,285,285,284,281,262,250,245,248],"all_points_y":[10,9,21,32,41,41,40,21,10]},"region_attributes":{"Type":"Bright"}},{"shape_attributes":{"name":"polyline","all_points_x":[237,285,289,291,278,271,251,236,235,238],"all_points_y":[11,10,42,45,52,58,60,41,20,11]},"region_attributes":{"Type":"Bright"}},{"shape_attributes":{"name":"ellipse","cx":160,"cy":311,"rx":37,"ry":22.847,"theta":0.405},"region_attributes":{"Type":"Bright"}},{"shape_attributes":{"name":"circle","cx":231,"cy":132,"r":79},"region_attributes":{"Type":"Faint"}}],"file_attributes":{}},"Ghost_img_D00158728.jpg38033":{"filename":"Ghost_img_D00158728.jpg","size":38033,"regions":[{"shape_attributes":{"name":"polyline","all_points_x":[231,289,290,304,304,304,290,282,272,265,246,228,191,180,210,201,182,175,169,188,151,141,158,233,231],"all_points_y":[10,10,42,40,65,76,83,130,175,196,198,202,292,289,169,169,209,208,208,157,204,200,143,23,12]},"region_attributes":{"Type":"Rays"}}],"file_attributes":{}},"Ghost_img_D00704920.jpg41176":{"filename":"Ghost_img_D00704920.jpg","size":41176,"regions":[{"shape_attributes":{"name":"ellipse","cx":308,"cy":107,"rx":40.311,"ry":18,"theta":0.768},"region_attributes":{"Type":"Bright"}},{"shape_attributes":{"name":"circle","cx":97,"cy":292,"r":16.492},"region_attributes":{"Type":"Bright"}},{"shape_attributes":{"name":"polyline","all_points_x":[50,74,75,90,71,51,51],"all_points_y":[326,326,341,341,302,296,324]},"region_attributes":{"Type":"Bright"}},{"shape_attributes":{"name":"circle","cx":141,"cy":257,"r":78.102},"region_attributes":{"Type":"Faint"}},{"shape_attributes":{"name":"circle","cx":173,"cy":220,"r":119},"region_attributes":{"Type":"Faint"}},{"shape_attributes":{"name":"circle","cx":246,"cy":118,"r":15},"region_attributes":{"Type":"Faint"}}],"file_attributes":{}},"Ghost_img_D00260592.jpg35627":{"filename":"Ghost_img_D00260592.jpg","size":35627,"regions":[{"shape_attributes":{"name":"polyline","all_points_x":[21,22,51,65,162,151,77,133,80,139,129,85,49,49,48,2,2,21,21],"all_points_y":[236,282,289,264,263,230,237,211,212,177,174,172,197,201,204,203,230,231,238]},"region_attributes":{"Type":"Rays"}}],"file_attributes":{}},"Ghost_img_D00261292.jpg34433":{"filename":"Ghost_img_D00261292.jpg","size":34433,"regions":[{"shape_attributes":{"name":"polyline","all_points_x":[300,318,319,308,297,300],"all_points_y":[43,43,68,78,60,45]},"region_attributes":{"Type":"Bright"}},{"shape_attributes":{"name":"circle","cx":282,"cy":102,"r":16.763},"region_attributes":{"Type":"Faint"}},{"shape_attributes":{"name":"ellipse","cx":128,"cy":295,"rx":42.012,"ry":23,"theta":0.667},"region_attributes":{"Type":"Faint"}}],"file_attributes":{}},"Ghost_img_D00610031.jpg37146":{"filename":"Ghost_img_D00610031.jpg","size":37146,"regions":[{"shape_attributes":{"name":"circle","cx":169,"cy":116,"r":13},"region_attributes":{"Type":"Bright"}},{"shape_attributes":{"name":"circle","cx":155,"cy":80,"r":16},"region_attributes":{"Type":"Bright"}},{"shape_attributes":{"name":"circle","cx":156,"cy":83,"r":29},"region_attributes":{"Type":"Faint"}},{"shape_attributes":{"name":"circle","cx":212,"cy":243,"r":11},"region_attributes":{"Type":"Bright"}},{"shape_attributes":{"name":"ellipse","cx":222,"cy":262,"rx":39,"ry":28,"theta":0},"region_attributes":{"Type":"Faint"}}],"file_attributes":{}},"Ghost_img_D00691254.jpg37015":{"filename":"Ghost_img_D00691254.jpg","size":37015,"regions":[{"shape_attributes":{"name":"ellipse","cx":71,"cy":276,"rx":32.757,"ry":16,"theta":1.025},"region_attributes":{"Type":"Bright"}},{"shape_attributes":{"name":"circle","cx":322,"cy":132,"r":14},"region_attributes":{"Type":"Bright"}},{"shape_attributes":{"name":"polyline","all_points_x":[331,377,380,351,327,327,333],"all_points_y":[121,118,132,137,133,120,121]},"region_attributes":{"Type":"Bright"}}],"file_attributes":{}},"Ghost_img_D00251881.jpg33448":{"filename":"Ghost_img_D00251881.jpg","size":33448,"regions":[{"shape_attributes":{"name":"polyline","all_points_x":[398,308,334,398,399],"all_points_y":[185,184,162,172,184]},"region_attributes":{"Type":"Rays"}},{"shape_attributes":{"name":"polyline","all_points_x":[301,398,398,346,302],"all_points_y":[210,192,203,224,210]},"region_attributes":{"Type":"Rays"}},{"shape_attributes":{"name":"ellipse","cx":29,"cy":223,"rx":27,"ry":16,"theta":0},"region_attributes":{"Type":"Faint"}}],"file_attributes":{}},"Ghost_img_D00785337.jpg36832":{"filename":"Ghost_img_D00785337.jpg","size":36832,"regions":[{"shape_attributes":{"name":"ellipse","cx":179,"cy":115,"rx":37,"ry":30,"theta":0},"region_attributes":{"Type":"Faint"}},{"shape_attributes":{"name":"ellipse","cx":229,"cy":308,"rx":14,"ry":14,"theta":0},"region_attributes":{"Type":"Faint"}},{"shape_attributes":{"name":"circle","cx":240,"cy":351,"r":17.263},"region_attributes":{"Type":"Bright"}},{"shape_attributes":{"name":"polyline","all_points_x":[210,228,230,247,275,270,254,235,223,211,211,211],"all_points_y":[360,360,379,380,367,337,329,322,325,341,354,359]},"region_attributes":{"Type":"Faint"}},{"shape_attributes":{"name":"circle","cx":205,"cy":235,"r":123},"region_attributes":{"Type":"Faint"}}],"file_attributes":{}},"Ghost_img_D00499393.jpg37495":{"filename":"Ghost_img_D00499393.jpg","size":37495,"regions":[{"shape_attributes":{"name":"ellipse","cx":107,"cy":274,"rx":33,"ry":21.932,"theta":-2.324},"region_attributes":{"Type":"Bright"}},{"shape_attributes":{"name":"circle","cx":302,"cy":124,"r":14.142},"region_attributes":{"Type":"Faint"}},{"shape_attributes":{"name":"polyline","all_points_x":[321,349,349,371,365,347,330,317,314,321],"all_points_y":[73,73,108,106,118,119,118,102,81,73]},"region_attributes":{"Type":"Bright"}},{"shape_attributes":{"name":"circle","cx":261,"cy":154,"r":77},"region_attributes":{"Type":"Faint"}},{"shape_attributes":{"name":"circle","cx":229,"cy":174,"r":128},"region_attributes":{"Type":"Faint"}}],"file_attributes":{}},"Ghost_img_D00262379.jpg37682":{"filename":"Ghost_img_D00262379.jpg","size":37682,"regions":[{"shape_attributes":{"name":"polyline","all_points_x":[329,348,350,317,292,331],"all_points_y":[77,75,92,139,125,76]},"region_attributes":{"Type":"Rays"}},{"shape_attributes":{"name":"polyline","all_points_x":[321,321,273,281,322],"all_points_y":[68,41,72,98,67]},"region_attributes":{"Type":"Rays"}},{"shape_attributes":{"name":"polyline","all_points_x":[50,48,70,85,79,50],"all_points_y":[75,104,102,77,73,74]},"region_attributes":{"Type":"Rays"}}],"file_attributes":{}},"Ghost_img_D00243153.jpg37997":{"filename":"Ghost_img_D00243153.jpg","size":37997,"regions":[{"shape_attributes":{"name":"polyline","all_points_x":[352,351,379,381,344,303,250,205,201,247,188,192,251,115,102,195,171,79,79,233,285,294,324,330,351,352],"all_points_y":[82,106,107,160,201,216,239,274,261,210,236,209,176,225,218,169,162,168,153,117,104,87,83,78,75,88]},"region_attributes":{"Type":"Rays"}},{"shape_attributes":{"name":"polyline","all_points_x":[318,318,306,280,290,319],"all_points_y":[50,43,43,66,73,50]},"region_attributes":{"Type":"Rays"}}],"file_attributes":{}},"Ghost_img_D00267299.jpg35611":{"filename":"Ghost_img_D00267299.jpg","size":35611,"regions":[{"shape_attributes":{"name":"polyline","all_points_x":[227,289,289,264,251,230,214,213,213,229,229],"all_points_y":[391,391,353,314,335,335,331,345,359,360,389]},"region_attributes":{"Type":"Rays"}}],"file_attributes":{}},"Ghost_img_D00794113.jpg36984":{"filename":"Ghost_img_D00794113.jpg","size":36984,"regions":[{"shape_attributes":{"name":"ellipse","cx":19,"cy":188,"rx":9,"ry":40.2,"theta":0.1},"region_attributes":{"Type":"Bright"}},{"shape_attributes":{"name":"circle","cx":349,"cy":208,"r":19},"region_attributes":{"Type":"Bright"}},{"shape_attributes":{"name":"polyline","all_points_x":[393,398,397,392,389,391,393,394],"all_points_y":[233,232,184,194,208,229,230,233]},"region_attributes":{"Type":"Faint"}}],"file_attributes":{}},"Ghost_img_D00161887.jpg37801":{"filename":"Ghost_img_D00161887.jpg","size":37801,"regions":[{"shape_attributes":{"name":"polyline","all_points_x":[238,289,289,298,281,235,265,253,211,167,220,230,237],"all_points_y":[392,394,355,355,284,279,362,365,293,285,361,361,392]},"region_attributes":{"Type":"Rays"}}],"file_attributes":{}},"Ghost_img_D00253786.jpg35332":{"filename":"Ghost_img_D00253786.jpg","size":35332,"regions":[{"shape_attributes":{"name":"polyline","all_points_x":[124,214,207,191,207,170,165,154,161,151,145,142,141,129,123,124],"all_points_y":[11,13,36,36,63,66,41,41,87,98,100,119,119,109,12,11]},"region_attributes":{"Type":"Rays"}},{"shape_attributes":{"name":"polyline","all_points_x":[329,356,356,379,379,382,382,374,352,344,329],"all_points_y":[115,110,104,106,129,162,167,167,150,128,115]},"region_attributes":{"Type":"Rays"}},{"shape_attributes":{"name":"polyline","all_points_x":[233,243,239,258,260,234,234,234],"all_points_y":[381,377,340,352,391,391,385,382]},"region_attributes":{"Type":"Rays"}}],"file_attributes":{}},"Ghost_img_D00243648.jpg36507":{"filename":"Ghost_img_D00243648.jpg","size":36507,"regions":[{"shape_attributes":{"name":"polyline","all_points_x":[267,286,288,271,255,279,271,240,230,267],"all_points_y":[12,11,26,101,100,18,16,75,56,11]},"region_attributes":{"Type":"Rays"}}],"file_attributes":{}},"Ghost_img_D00281641.jpg37365":{"filename":"Ghost_img_D00281641.jpg","size":37365,"regions":[{"shape_attributes":{"name":"polyline","all_points_x":[253,290,290,278,257,253,255],"all_points_y":[10,9,22,29,27,12,10]},"region_attributes":{"Type":"Bright"}},{"shape_attributes":{"name":"polyline","all_points_x":[243,289,289,265,236,243],"all_points_y":[12,9,38,42,38,13]},"region_attributes":{"Type":"Faint"}},{"shape_attributes":{"name":"circle","cx":250,"cy":70,"r":14.036},"region_attributes":{"Type":"Faint"}},{"shape_attributes":{"name":"polyline","all_points_x":[197,228,229,192,192,213,237,243,222,202,197,197,197],"all_points_y":[169,169,183,182,195,201,195,159,146,146,154,164,167]},"region_attributes":{"Type":"Bright"}},{"shape_attributes":{"name":"polyline","all_points_x":[21,20,158,160,159,39,19],"all_points_y":[257,234,225,245,259,262,258]},"region_attributes":{"Type":"Rays"}},{"shape_attributes":{"name":"polyline","all_points_x":[0,97,70,109,91,51,51,1,0],"all_points_y":[226,208,201,170,160,184,205,203,227]},"region_attributes":{"Type":"Rays"}},{"shape_attributes":{"name":"ellipse","cx":150,"cy":343,"rx":34.205,"ry":16,"theta":-2.875},"region_attributes":{"Type":"Bright"}}],"file_attributes":{}},"Ghost_img_D00600213.jpg37951":{"filename":"Ghost_img_D00600213.jpg","size":37951,"regions":[{"shape_attributes":{"name":"ellipse","cx":215,"cy":107,"rx":39.013,"ry":27,"theta":0.026},"region_attributes":{"Type":"Bright"}},{"shape_attributes":{"name":"polyline","all_points_x":[144,173,172,163,148,144,145],"all_points_y":[363,361,392,392,382,364,364]},"region_attributes":{"Type":"Bright"}},{"shape_attributes":{"name":"polyline","all_points_x":[199,142,163,194,202,199],"all_points_y":[344,346,330,331,345,345]},"region_attributes":{"Type":"Bright"}},{"shape_attributes":{"name":"circle","cx":181,"cy":312,"r":15},"region_attributes":{"Type":"Bright"}},{"shape_attributes":{"name":"circle","cx":189,"cy":267,"r":77.006},"region_attributes":{"Type":"Faint"}},{"shape_attributes":{"name":"circle","cx":195,"cy":230,"r":120.416},"region_attributes":{"Type":"Faint"}}],"file_attributes":{}},"Ghost_img_D00473497.jpg39280":{"filename":"Ghost_img_D00473497.jpg","size":39280,"regions":[{"shape_attributes":{"name":"ellipse","cx":163,"cy":84,"rx":35.468,"ry":27,"theta":-0.375},"region_attributes":{"Type":"Bright"}},{"shape_attributes":{"name":"circle","cx":237,"cy":324,"r":17},"region_attributes":{"Type":"Bright"}},{"shape_attributes":{"name":"polyline","all_points_x":[232,232,294,293,232],"all_points_y":[373,395,394,377,375]},"region_attributes":{"Type":"Bright"}},{"shape_attributes":{"name":"polyline","all_points_x":[277,232,235,261,279,277],"all_points_y":[361,363,345,345,358,361]},"region_attributes":{"Type":"Bright"}},{"shape_attributes":{"name":"circle","cx":218,"cy":266,"r":87},"region_attributes":{"Type":"Faint"}}],"file_attributes":{}},"Ghost_img_D00276989.jpg33809":{"filename":"Ghost_img_D00276989.jpg","size":33809,"regions":[{"shape_attributes":{"name":"polyline","all_points_x":[111,111,143,161,112,111],"all_points_y":[11,43,76,60,10,12]},"region_attributes":{"Type":"Rays"}},{"shape_attributes":{"name":"polyline","all_points_x":[102,80,80,94,114,100],"all_points_y":[43,43,58,79,76,43]},"region_attributes":{"Type":"Rays"}},{"shape_attributes":{"name":"ellipse","cx":259,"cy":37,"rx":22.472,"ry":18,"theta":2.134},"region_attributes":{"Type":"Faint"}},{"shape_attributes":{"name":"circle","cx":244,"cy":89,"r":18},"region_attributes":{"Type":"Faint"}},{"shape_attributes":{"name":"ellipse","cx":162,"cy":298,"rx":34.205,"ry":28,"theta":0.661},"region_attributes":{"Type":"Faint"}},{"shape_attributes":{"name":"circle","cx":81,"cy":135,"r":19.105},"region_attributes":{"Type":"Faint"}}],"file_attributes":{}},"Ghost_img_D00809790.jpg40692":{"filename":"Ghost_img_D00809790.jpg","size":40692,"regions":[{"shape_attributes":{"name":"ellipse","cx":294,"cy":244,"rx":24,"ry":38.626,"theta":-2.771},"region_attributes":{"Type":"Bright"}},{"shape_attributes":{"name":"circle","cx":90,"cy":151,"r":16},"region_attributes":{"Type":"Bright"}},{"shape_attributes":{"name":"polyline","all_points_x":[21,19,46,67,75,71,53,51,51,23,21],"all_points_y":[108,148,161,153,130,107,98,98,107,103,108]},"region_attributes":{"Type":"Bright"}},{"shape_attributes":{"name":"circle","cx":40,"cy":127,"r":20.591},"region_attributes":{"Type":"Bright"}},{"shape_attributes":{"name":"circle","cx":133,"cy":166,"r":76.026},"region_attributes":{"Type":"Faint"}},{"shape_attributes":{"name":"circle","cx":168,"cy":178,"r":122.037},"region_attributes":{"Type":"Faint"}}],"file_attributes":{}},"Ghost_img_D00273637.jpg33479":{"filename":"Ghost_img_D00273637.jpg","size":33479,"regions":[{"shape_attributes":{"name":"polyline","all_points_x":[111,111,163,183,228,189,119,113],"all_points_y":[13,35,99,99,141,88,13,13]},"region_attributes":{"Type":"Rays"}},{"shape_attributes":{"name":"polyline","all_points_x":[82,103,137,125,93,83,83],"all_points_y":[42,42,128,130,76,44,43]},"region_attributes":{"Type":"Rays"}},{"shape_attributes":{"name":"circle","cx":55,"cy":231,"r":19},"region_attributes":{"Type":"Faint"}}],"file_attributes":{}},"Ghost_img_D00283436.jpg36441":{"filename":"Ghost_img_D00283436.jpg","size":36441,"regions":[{"shape_attributes":{"name":"polyline","all_points_x":[82,111,111,126,127,128,112,97,81,83],"all_points_y":[43,42,13,12,31,41,56,67,67,45]},"region_attributes":{"Type":"Bright"}},{"shape_attributes":{"name":"polyline","all_points_x":[25,47,84,111,146,118,120,83,80,80,50,49,26],"all_points_y":[294,254,271,245,273,297,344,351,352,326,326,295,294]},"region_attributes":{"Type":"Rays"}}],"file_attributes":{}},"Ghost_img_D00590555.jpg34852":{"filename":"Ghost_img_D00590555.jpg","size":34852,"regions":[{"shape_attributes":{"name":"circle","cx":164,"cy":317,"r":15.033},"region_attributes":{"Type":"Bright"}},{"shape_attributes":{"name":"ellipse","cx":216,"cy":143,"rx":35,"ry":31.385,"theta":-2.607},"region_attributes":{"Type":"Faint"}}],"file_attributes":{}},"Ghost_img_D00772011.jpg37191":{"filename":"Ghost_img_D00772011.jpg","size":37191,"regions":[{"shape_attributes":{"name":"polyline","all_points_x":[80,113,101,75,55,68,90,112,117,79,79,82],"all_points_y":[169,171,186,186,163,133,128,134,150,151,167,169]},"region_attributes":{"Type":"Bright"}},{"shape_attributes":{"name":"ellipse","cx":255,"cy":221,"rx":31,"ry":35,"theta":0},"region_attributes":{"Type":"Bright"}},{"shape_attributes":{"name":"circle","cx":157,"cy":186,"r":76.903},"region_attributes":{"Type":"Faint"}},{"shape_attributes":{"name":"circle","cx":177,"cy":187,"r":117},"region_attributes":{"Type":"Faint"}}],"file_attributes":{}},"Ghost_img_D00512548.jpg35523":{"filename":"Ghost_img_D00512548.jpg","size":35523,"regions":[{"shape_attributes":{"name":"polyline","all_points_x":[225,247,288,261,223],"all_points_y":[162,184,133,128,164]},"region_attributes":{"Type":"Rays"}}],"file_attributes":{}},"Ghost_img_D00465603.jpg38318":{"filename":"Ghost_img_D00465603.jpg","size":38318,"regions":[{"shape_attributes":{"name":"polyline","all_points_x":[109,138,138,132,119,107,107,109],"all_points_y":[299,299,310,320,322,317,301,299]},"region_attributes":{"Type":"Bright"}},{"shape_attributes":{"name":"circle","cx":124,"cy":301,"r":29.069},"region_attributes":{"Type":"Faint"}},{"shape_attributes":{"name":"ellipse","cx":238,"cy":148,"rx":34,"ry":38.601,"theta":2.503},"region_attributes":{"Type":"Bright"}},{"shape_attributes":{"name":"circle","cx":168,"cy":246,"r":81.025},"region_attributes":{"Type":"Faint"}}],"file_attributes":{}},"Ghost_img_D00615510.jpg37971":{"filename":"Ghost_img_D00615510.jpg","size":37971,"regions":[{"shape_attributes":{"name":"ellipse","cx":218,"cy":283,"rx":36.401,"ry":29,"theta":-0.278},"region_attributes":{"Type":"Faint"}},{"shape_attributes":{"name":"circle","cx":174,"cy":97,"r":17},"region_attributes":{"Type":"Bright"}},{"shape_attributes":{"name":"circle","cx":162,"cy":50,"r":17},"region_attributes":{"Type":"Bright"}},{"shape_attributes":{"name":"circle","cx":164,"cy":53,"r":29},"region_attributes":{"Type":"Faint"}},{"shape_attributes":{"name":"ellipse","cx":240,"cy":69,"rx":16.553,"ry":12,"theta":-0.437},"region_attributes":{"Type":"Faint"}}],"file_attributes":{}},"Ghost_img_D00497776.jpg34407":{"filename":"Ghost_img_D00497776.jpg","size":34407,"regions":[{"shape_attributes":{"name":"polyline","all_points_x":[51,51,51,70,79,72,57,48,52],"all_points_y":[188,205,213,213,199,179,177,179,190]},"region_attributes":{"Type":"Bright"}},{"shape_attributes":{"name":"circle","cx":100,"cy":192,"r":12},"region_attributes":{"Type":"Faint"}}],"file_attributes":{}},"Ghost_img_D00280721.jpg37599":{"filename":"Ghost_img_D00280721.jpg","size":37599,"regions":[{"shape_attributes":{"name":"circle","cx":225,"cy":164,"r":39.013},"region_attributes":{"Type":"Bright"}},{"shape_attributes":{"name":"circle","cx":138,"cy":218,"r":14.142},"region_attributes":{"Type":"Bright"}},{"shape_attributes":{"name":"polyline","all_points_x":[141,171,166,140,122,125,155,162,162,139,139,147],"all_points_y":[284,282,301,303,287,258,254,260,265,265,281,281]},"region_attributes":{"Type":"Bright"}},{"shape_attributes":{"name":"circle","cx":189,"cy":217,"r":123.065},"region_attributes":{"Type":"Faint"}},{"shape_attributes":{"name":"polyline","all_points_x":[398,327,338,398,397],"all_points_y":[216,218,236,230,217]},"region_attributes":{"Type":"Rays"}},{"shape_attributes":{"name":"polyline","all_points_x":[112,112,133,123,111],"all_points_y":[375,391,369,356,377]},"region_attributes":{"Type":"Rays"}}],"file_attributes":{}},"Ghost_img_D00268371.jpg39416":{"filename":"Ghost_img_D00268371.jpg","size":39416,"regions":[{"shape_attributes":{"name":"polyline","all_points_x":[399,384,369,381,399,398],"all_points_y":[218,218,196,168,171,216]},"region_attributes":{"Type":"Bright"}}],"file_attributes":{}},"Ghost_img_D00491102.jpg37419":{"filename":"Ghost_img_D00491102.jpg","size":37419,"regions":[{"shape_attributes":{"name":"circle","cx":118,"cy":137,"r":14.036},"region_attributes":{"Type":"Bright"}},{"shape_attributes":{"name":"circle","cx":83,"cy":109,"r":19},"region_attributes":{"Type":"Bright"}},{"shape_attributes":{"name":"circle","cx":82,"cy":107,"r":28},"region_attributes":{"Type":"Faint"}},{"shape_attributes":{"name":"ellipse","cx":261,"cy":248,"rx":36.235,"ry":33,"theta":-0.688},"region_attributes":{"Type":"Faint"}}],"file_attributes":{}},"Ghost_img_D00251875.jpg36030":{"filename":"Ghost_img_D00251875.jpg","size":36030,"regions":[{"shape_attributes":{"name":"polyline","all_points_x":[20,20,159,153,114,18],"all_points_y":[138,159,166,153,135,139]},"region_attributes":{"Type":"Rays"}},{"shape_attributes":{"name":"polyline","all_points_x":[0,0,48,50,81,76,10,4,1],"all_points_y":[171,183,186,202,213,190,170,170,170]},"region_attributes":{"Type":"Rays"}}],"file_attributes":{}},"Ghost_img_D00256582.jpg38116":{"filename":"Ghost_img_D00256582.jpg","size":38116,"regions":[{"shape_attributes":{"name":"polyline","all_points_x":[276,248,267,288,287,277,274,271],"all_points_y":[12,46,51,33,11,12,13,20]},"region_attributes":{"Type":"Rays"}},{"shape_attributes":{"name":"polyline","all_points_x":[299,288,303,313,300,298],"all_points_y":[44,70,72,45,41,46]},"region_attributes":{"Type":"Rays"}}],"file_attributes":{}},"Ghost_img_D00682175.jpg39044":{"filename":"Ghost_img_D00682175.jpg","size":39044,"regions":[{"shape_attributes":{"name":"ellipse","cx":166,"cy":229,"rx":33,"ry":40.706,"theta":-0.486},"region_attributes":{"Type":"Bright"}},{"shape_attributes":{"name":"polyline","all_points_x":[294,287,263,241,254,290,302,302,260,260,294,294],"all_points_y":[153,168,163,142,113,107,131,133,135,155,152,156]},"region_attributes":{"Type":"Bright"}},{"shape_attributes":{"name":"circle","cx":229,"cy":177,"r":72},"region_attributes":{"Type":"Faint"}},{"shape_attributes":{"name":"circle","cx":222,"cy":183,"r":121.037},"region_attributes":{"Type":"Faint"}}],"file_attributes":{}},"Ghost_img_D00261231.jpg34026":{"filename":"Ghost_img_D00261231.jpg","size":34026,"regions":[{"shape_attributes":{"name":"polyline","all_points_x":[110,109,123,139,139,121,110],"all_points_y":[12,35,106,107,59,10,12]},"region_attributes":{"Type":"Rays"}},{"shape_attributes":{"name":"polyline","all_points_x":[136,162,202,169,169,158,155,137,137],"all_points_y":[12,76,78,40,26,13,12,12,15]},"region_attributes":{"Type":"Rays"}}],"file_attributes":{}},"Ghost_img_D00354875.jpg34642":{"filename":"Ghost_img_D00354875.jpg","size":34642,"regions":[{"shape_attributes":{"name":"circle","cx":96,"cy":69,"r":20},"region_attributes":{"Type":"Bright"}},{"shape_attributes":{"name":"ellipse","cx":261,"cy":273,"rx":37.014,"ry":24,"theta":2.471},"region_attributes":{"Type":"Faint"}}],"file_attributes":{}},"Ghost_img_D00261168.jpg38382":{"filename":"Ghost_img_D00261168.jpg","size":38382,"regions":[{"shape_attributes":{"name":"polyline","all_points_x":[185,211,209,195,186,186,187,187],"all_points_y":[359,359,334,334,341,356,356,359]},"region_attributes":{"Type":"Bright"}},{"shape_attributes":{"name":"circle","cx":196,"cy":224,"r":136},"region_attributes":{"Type":"Faint"}},{"shape_attributes":{"name":"polyline","all_points_x":[162,128,121,166,245,276,267,246,242,232,161,161],"all_points_y":[356,324,266,212,227,285,322,348,356,358,359,353]},"region_attributes":{"Type":"Faint"}},{"shape_attributes":{"name":"polyline","all_points_x":[121,167,167,228,229,285,286,226,137,121],"all_points_y":[12,12,40,41,11,7,40,66,44,12]},"region_attributes":{"Type":"Faint"}}],"file_attributes":{}},"Ghost_img_D00166263.jpg39444":{"filename":"Ghost_img_D00166263.jpg","size":39444,"regions":[{"shape_attributes":{"name":"polyline","all_points_x":[20,20,71,64,20],"all_points_y":[154,170,167,143,153]},"region_attributes":{"Type":"Rays"}}],"file_attributes":{}},"Ghost_img_D00571695.jpg38773":{"filename":"Ghost_img_D00571695.jpg","size":38773,"regions":[{"shape_attributes":{"name":"circle","cx":143,"cy":310,"r":16},"region_attributes":{"Type":"Bright"}},{"shape_attributes":{"name":"polyline","all_points_x":[110,110,126,138,138,122,110,92,93,110,110],"all_points_y":[363,382,376,359,343,337,337,347,359,361,363]},"region_attributes":{"Type":"Bright"}},{"shape_attributes":{"name":"ellipse","cx":247,"cy":105,"rx":31.064,"ry":23,"theta":0.579},"region_attributes":{"Type":"Faint"}}],"file_attributes":{}},"Ghost_img_D00398763.jpg35891":{"filename":"Ghost_img_D00398763.jpg","size":35891,"regions":[{"shape_attributes":{"name":"circle","cx":156,"cy":88,"r":14.036},"region_attributes":{"Type":"Faint"}},{"shape_attributes":{"name":"polyline","all_points_x":[234,263,266,249,236,232,232],"all_points_y":[394,394,383,375,375,375,393]},"region_attributes":{"Type":"Faint"}}],"file_attributes":{}},"Ghost_img_D00696887.jpg38578":{"filename":"Ghost_img_D00696887.jpg","size":38578,"regions":[{"shape_attributes":{"name":"polyline","all_points_x":[81,80,93,96,96,82,70,66,64,70,79,82],"all_points_y":[282,300,300,300,310,313,310,303,291,282,282,283]},"region_attributes":{"Type":"Bright"}},{"shape_attributes":{"name":"ellipse","cx":264,"cy":149,"rx":36.878,"ry":31,"theta":0.709},"region_attributes":{"Type":"Bright"}},{"shape_attributes":{"name":"polyline","all_points_x":[83,114,108,89,66,53,54,78,99,103,82,84],"all_points_y":[297,296,312,322,321,300,272,263,262,279,282,300]},"region_attributes":{"Type":"Faint"}},{"shape_attributes":{"name":"circle","cx":151,"cy":241,"r":80},"region_attributes":{"Type":"Faint"}}],"file_attributes":{}},"Ghost_img_D00275637.jpg37118":{"filename":"Ghost_img_D00275637.jpg","size":37118,"regions":[{"shape_attributes":{"name":"polyline","all_points_x":[259,275,280,257,259],"all_points_y":[11,11,46,57,11]},"region_attributes":{"Type":"Rays"}},{"shape_attributes":{"name":"polyline","all_points_x":[233,233,249,242,234],"all_points_y":[12,30,46,11,11]},"region_attributes":{"Type":"Rays"}}],"file_attributes":{}},"Ghost_img_D00231498.jpg38429":{"filename":"Ghost_img_D00231498.jpg","size":38429,"regions":[{"shape_attributes":{"name":"polyline","all_points_x":[20,21,1,1,47,53,104,106,25,28,140,165,20,20],"all_points_y":[139,170,170,184,185,194,204,193,163,154,170,152,139,142]},"region_attributes":{"Type":"Rays"}},{"shape_attributes":{"name":"polyline","all_points_x":[111,113,139,177,157,131,147,128,111,81,95,108,110],"all_points_y":[364,392,392,318,313,368,312,312,347,350,359,361,366]},"region_attributes":{"Type":"Rays"}}],"file_attributes":{}},"Ghost_img_D00243479.jpg35186":{"filename":"Ghost_img_D00243479.jpg","size":35186,"regions":[{"shape_attributes":{"name":"polyline","all_points_x":[20,21,99,125,124,43,20,19,20],"all_points_y":[244,264,269,258,239,239,244,248,245]},"region_attributes":{"Type":"Rays"}},{"shape_attributes":{"name":"polyline","all_points_x":[0,19,62,40,26,1,1],"all_points_y":[232,231,210,202,202,215,230]},"region_attributes":{"Type":"Rays"}}],"file_attributes":{}},"Ghost_img_D00231072.jpg37804":{"filename":"Ghost_img_D00231072.jpg","size":37804,"regions":[{"shape_attributes":{"name":"polyline","all_points_x":[289,319,320,335,270,257,281,267,271,262,256,284,251,241,290],"all_points_y":[360,360,327,327,197,200,253,250,262,262,269,317,302,318,361]},"region_attributes":{"Type":"Rays"}}],"file_attributes":{}},"Ghost_img_D00243162.jpg36868":{"filename":"Ghost_img_D00243162.jpg","size":36868,"regions":[{"shape_attributes":{"name":"polyline","all_points_x":[318,300,182,198,219,199,199,228,260,291,331,352,352,321,320,318],"all_points_y":[354,349,272,256,257,214,197,196,232,227,277,306,326,326,353,353]},"region_attributes":{"Type":"Rays"}}],"file_attributes":{}},"Ghost_img_D00268941.jpg39627":{"filename":"Ghost_img_D00268941.jpg","size":39627,"regions":[{"shape_attributes":{"name":"polyline","all_points_x":[224,198,216,230,231,253,258,264,254,234,232,224,224],"all_points_y":[357,221,221,297,187,197,296,328,393,391,358,358,355]},"region_attributes":{"Type":"Rays"}},{"shape_attributes":{"name":"polyline","all_points_x":[191,217,179,162,162,168,188,191],"all_points_y":[359,359,233,225,251,305,347,358]},"region_attributes":{"Type":"Rays"}}],"file_attributes":{}},"Ghost_img_D00162280.jpg37727":{"filename":"Ghost_img_D00162280.jpg","size":37727,"regions":[{"shape_attributes":{"name":"circle","cx":261,"cy":154,"r":11.705},"region_attributes":{"Type":"Bright"}},{"shape_attributes":{"name":"circle","cx":262,"cy":153,"r":24.187},"region_attributes":{"Type":"Bright"}},{"shape_attributes":{"name":"ellipse","cx":173,"cy":223,"rx":36.125,"ry":35,"theta":-0.083},"region_attributes":{"Type":"Bright"}},{"shape_attributes":{"name":"circle","cx":222,"cy":193,"r":120.004},"region_attributes":{"Type":"Faint"}}],"file_attributes":{}},"Ghost_img_D00237687.jpg38712":{"filename":"Ghost_img_D00237687.jpg","size":38712,"regions":[{"shape_attributes":{"name":"polyline","all_points_x":[21,55,68,70,21,21],"all_points_y":[270,260,260,287,289,270]},"region_attributes":{"Type":"Rays"}},{"shape_attributes":{"name":"polyline","all_points_x":[21,86,65,63,21,23,24],"all_points_y":[256,223,208,206,234,255,255]},"region_attributes":{"Type":"Rays"}},{"shape_attributes":{"name":"circle","cx":170,"cy":179,"r":11},"region_attributes":{"Type":"Bright"}},{"shape_attributes":{"name":"circle","cx":169,"cy":180,"r":24},"region_attributes":{"Type":"Faint"}},{"shape_attributes":{"name":"circle","cx":349,"cy":137,"r":16.125},"region_attributes":{"Type":"Faint"}},{"shape_attributes":{"name":"circle","cx":213,"cy":211,"r":38},"region_attributes":{"Type":"Faint"}},{"shape_attributes":{"name":"circle","cx":205,"cy":205,"r":120},"region_attributes":{"Type":"Faint"}}],"file_attributes":{}},"Ghost_img_D00614056.jpg37445":{"filename":"Ghost_img_D00614056.jpg","size":37445,"regions":[{"shape_attributes":{"name":"circle","cx":171,"cy":154,"r":16},"region_attributes":{"Type":"Bright"}}],"file_attributes":{}},"Ghost_img_D00579915.jpg35850":{"filename":"Ghost_img_D00579915.jpg","size":35850,"regions":[{"shape_attributes":{"name":"polyline","all_points_x":[230,230,236,249,260,269,229],"all_points_y":[11,34,39,40,37,11,10]},"region_attributes":{"Type":"Faint"}}],"file_attributes":{}},"Ghost_img_D00466890.jpg35512":{"filename":"Ghost_img_D00466890.jpg","size":35512,"regions":[{"shape_attributes":{"name":"circle","cx":161,"cy":108,"r":17.117},"region_attributes":{"Type":"Bright"}},{"shape_attributes":{"name":"circle","cx":139,"cy":63,"r":19.026},"region_attributes":{"Type":"Bright"}},{"shape_attributes":{"name":"polyline","all_points_x":[131,167,167,156,133,133],"all_points_y":[12,11,27,28,24,14]},"region_attributes":{"Type":"Bright"}},{"shape_attributes":{"name":"circle","cx":273,"cy":321,"r":15},"region_attributes":{"Type":"Faint"}},{"shape_attributes":{"name":"ellipse","cx":231,"cy":332,"rx":33,"ry":20.248,"theta":-0.353},"region_attributes":{"Type":"Faint"}},{"shape_attributes":{"name":"ellipse","cx":227,"cy":272,"rx":41.195,"ry":27,"theta":-0.097},"region_attributes":{"Type":"Faint"}}],"file_attributes":{}},"Ghost_img_D00266644.jpg40604":{"filename":"Ghost_img_D00266644.jpg","size":40604,"regions":[{"shape_attributes":{"name":"ellipse","cx":341,"cy":230,"rx":18.974,"ry":34,"theta":-2.82},"region_attributes":{"Type":"Bright"}},{"shape_attributes":{"name":"circle","cx":64,"cy":172,"r":16},"region_attributes":{"Type":"Bright"}},{"shape_attributes":{"name":"polyline","all_points_x":[2,3,38,41,31,20,19,30,30,30,1,2],"all_points_y":[172,185,186,168,142,125,148,150,164,167,172,175]},"region_attributes":{"Type":"Bright"}},{"shape_attributes":{"name":"circle","cx":113,"cy":183,"r":81.006},"region_attributes":{"Type":"Faint"}},{"shape_attributes":{"name":"circle","cx":166,"cy":195,"r":140.161},"region_attributes":{"Type":"Faint"}}],"file_attributes":{}},"Ghost_img_D00261204.jpg33960":{"filename":"Ghost_img_D00261204.jpg","size":33960,"regions":[{"shape_attributes":{"name":"ellipse","cx":133,"cy":22,"rx":9,"ry":11,"theta":0},"region_attributes":{"Type":"Faint"}},{"shape_attributes":{"name":"polyline","all_points_x":[51,52,19,19,56,78,118,138,76,79,57,51,51],"all_points_y":[77,103,107,136,167,133,148,148,111,86,76,76,78]},"region_attributes":{"Type":"Rays"}}],"file_attributes":{}},"Ghost_img_D00271323.jpg38841":{"filename":"Ghost_img_D00271323.jpg","size":38841,"regions":[{"shape_attributes":{"name":"polyline","all_points_x":[52,53,82,80,95,95,166,143,107,72,21,22,52],"all_points_y":[296,326,325,345,325,296,243,232,243,262,256,290,297]},"region_attributes":{"Type":"Rays"}}],"file_attributes":{}},"Ghost_img_D00163447.jpg35090":{"filename":"Ghost_img_D00163447.jpg","size":35090,"regions":[{"shape_attributes":{"name":"polyline","all_points_x":[398,309,381,397,399,399],"all_points_y":[206,221,229,229,229,204]},"region_attributes":{"Type":"Rays"}},{"shape_attributes":{"name":"polyline","all_points_x":[347,398,398,362,350],"all_points_y":[186,197,177,170,186]},"region_attributes":{"Type":"Rays"}}],"file_attributes":{}},"Ghost_img_D00714861.jpg35589":{"filename":"Ghost_img_D00714861.jpg","size":35589,"regions":[{"shape_attributes":{"name":"circle","cx":118,"cy":84,"r":18},"region_attributes":{"Type":"Bright"}},{"shape_attributes":{"name":"circle","cx":120,"cy":85,"r":28},"region_attributes":{"Type":"Faint"}},{"shape_attributes":{"name":"circle","cx":143,"cy":119,"r":13},"region_attributes":{"Type":"Faint"}},{"shape_attributes":{"name":"ellipse","cx":242,"cy":262,"rx":37,"ry":30.48,"theta":-0.716},"region_attributes":{"Type":"Faint"}},{"shape_attributes":{"name":"circle","cx":179,"cy":176,"r":144.003},"region_attributes":{"Type":"Faint"}}],"file_attributes":{}},"Ghost_img_D00269882.jpg36020":{"filename":"Ghost_img_D00269882.jpg","size":36020,"regions":[{"shape_attributes":{"name":"circle","cx":341,"cy":95,"r":12},"region_attributes":{"Type":"Faint"}}],"file_attributes":{}},"Ghost_img_D00259397.jpg38109":{"filename":"Ghost_img_D00259397.jpg","size":38109,"regions":[{"shape_attributes":{"name":"polyline","all_points_x":[112,166,167,167,181,191,180,155,163,141,129,113,112],"all_points_y":[12,11,37,41,42,72,71,26,97,105,43,22,13]},"region_attributes":{"Type":"Rays"}}],"file_attributes":{}},"Ghost_img_D00696570.jpg36993":{"filename":"Ghost_img_D00696570.jpg","size":36993,"regions":[{"shape_attributes":{"name":"ellipse","cx":151,"cy":64,"rx":32.894,"ry":14,"theta":2.801},"region_attributes":{"Type":"Faint"}},{"shape_attributes":{"name":"circle","cx":243,"cy":330,"r":15},"region_attributes":{"Type":"Faint"}},{"shape_attributes":{"name":"polyline","all_points_x":[240,288,283,262,246,241],"all_points_y":[393,394,379,373,380,394]},"region_attributes":{"Type":"Bright"}}],"file_attributes":{}}},"_via_attributes":{"region":{"Type":{"type":"dropdown","description":"","options":{"Bright":"","Faint":"","Rays":""},"default_options":{"Faint":true}}},"file":{}},"_via_data_format_version":"2.0.10","_via_image_id_list":["Ghost_img_D00270414.jpg38186","Ghost_img_D00360575.jpg38897","Ghost_img_D00239707.jpg37617","Ghost_img_D00240503.jpg37925","Ghost_img_D00237444.jpg35593","Ghost_img_D00487224.jpg40966","Ghost_img_D00510773.jpg35141","Ghost_img_D00799119.jpg42697","Ghost_img_D00701094.jpg40298","Ghost_img_D00243671.jpg43091","Ghost_img_D00251360.jpg37064","Ghost_img_D00396006.jpg33394","Ghost_img_D00686822.jpg42584","Ghost_img_D00243229.jpg36052","Ghost_img_D00240804.jpg36113","Ghost_img_D00776109.jpg36907","Ghost_img_D00703260.jpg36404","Ghost_img_D00484509.jpg39898","Ghost_img_D00281645.jpg36076","Ghost_img_D00158340.jpg35008","Ghost_img_D00281667.jpg36761","Ghost_img_D00247637.jpg34833","Ghost_img_D00491193.jpg36372","Ghost_img_D00261167.jpg37653","Ghost_img_D00264198.jpg35941","Ghost_img_D00804812.jpg37561","Ghost_img_D00162299.jpg38967","Ghost_img_D00578320.jpg41473","Ghost_img_D00670009.jpg42427","Ghost_img_D00403482.jpg38797","Ghost_img_D00157884.jpg37737","Ghost_img_D00252782.jpg34737","Ghost_img_D00720402.jpg38535","Ghost_img_D00361667.jpg35267","Ghost_img_D00270231.jpg35564","Ghost_img_D00274018.jpg33948","Ghost_img_D00717821.jpg34449","Ghost_img_D00239722.jpg36442","Ghost_img_D00704854.jpg38370","Ghost_img_D00158728.jpg38033","Ghost_img_D00704920.jpg41176","Ghost_img_D00260592.jpg35627","Ghost_img_D00261292.jpg34433","Ghost_img_D00610031.jpg37146","Ghost_img_D00691254.jpg37015","Ghost_img_D00251881.jpg33448","Ghost_img_D00785337.jpg36832","Ghost_img_D00499393.jpg37495","Ghost_img_D00262379.jpg37682","Ghost_img_D00243153.jpg37997","Ghost_img_D00267299.jpg35611","Ghost_img_D00794113.jpg36984","Ghost_img_D00161887.jpg37801","Ghost_img_D00253786.jpg35332","Ghost_img_D00243648.jpg36507","Ghost_img_D00281641.jpg37365","Ghost_img_D00600213.jpg37951","Ghost_img_D00473497.jpg39280","Ghost_img_D00276989.jpg33809","Ghost_img_D00809790.jpg40692","Ghost_img_D00273637.jpg33479","Ghost_img_D00283436.jpg36441","Ghost_img_D00590555.jpg34852","Ghost_img_D00772011.jpg37191","Ghost_img_D00512548.jpg35523","Ghost_img_D00465603.jpg38318","Ghost_img_D00615510.jpg37971","Ghost_img_D00497776.jpg34407","Ghost_img_D00280721.jpg37599","Ghost_img_D00268371.jpg39416","Ghost_img_D00491102.jpg37419","Ghost_img_D00251875.jpg36030","Ghost_img_D00256582.jpg38116","Ghost_img_D00682175.jpg39044","Ghost_img_D00261231.jpg34026","Ghost_img_D00354875.jpg34642","Ghost_img_D00261168.jpg38382","Ghost_img_D00166263.jpg39444","Ghost_img_D00571695.jpg38773","Ghost_img_D00398763.jpg35891","Ghost_img_D00696887.jpg38578","Ghost_img_D00275637.jpg37118","Ghost_img_D00231498.jpg38429","Ghost_img_D00243479.jpg35186","Ghost_img_D00231072.jpg37804","Ghost_img_D00243162.jpg36868","Ghost_img_D00268941.jpg39627","Ghost_img_D00162280.jpg37727","Ghost_img_D00237687.jpg38712","Ghost_img_D00614056.jpg37445","Ghost_img_D00579915.jpg35850","Ghost_img_D00466890.jpg35512","Ghost_img_D00266644.jpg40604","Ghost_img_D00261204.jpg33960","Ghost_img_D00271323.jpg38841","Ghost_img_D00163447.jpg35090","Ghost_img_D00714861.jpg35589","Ghost_img_D00269882.jpg36020","Ghost_img_D00259397.jpg38109","Ghost_img_D00696570.jpg36993"]}